hackerone_app_sdk/__init__.py
hackerone_app_sdk-0.18.0.dist-info/METADATA
hackerone_app_sdk-0.18.0.dist-info/WHEEL
hackerone_app_sdk-0.18.0.dist-info/top_level.txt
hackerone_app_sdk-0.18.0.dist-info/RECORD
