Metadata-Version: 2.4
Name: hackerone_app_sdk
Version: 0.18.0
Summary: POC package (beacon-only)
Dynamic: summary
